{
  "generated_at": "2026-06-23T18:40:44+08:00",
  "macro": [
    {
      "ticker": "DXY",
      "label": "美元指数",
      "value": "101.19",
      "pct": "+0.18%",
      "dir": "up",
      "price": 101.187,
      "chg_pct": 0.183,
      "updated": "2026-06-23 18:40:43"
    },
    {
      "ticker": "USDCNY",
      "label": "美元/人民币",
      "value": "6.7834",
      "pct": "+0.24%",
      "dir": "up",
      "price": 6.7834,
      "chg_pct": 0.241,
      "updated": "2026-06-23 18:40:43"
    },
    {
      "ticker": "US10Y",
      "label": "美债10Y收益率",
      "value": "4.51%",
      "pct": "+1.30%",
      "dir": "up",
      "price": 4.509,
      "chg_pct": 1.303,
      "updated": "2026-06-23 18:40:43"
    },
    {
      "ticker": "VIX",
      "label": "恐慌指数",
      "value": "19.70",
      "pct": "+14.00%",
      "dir": "up",
      "price": 19.7,
      "chg_pct": 14.005,
      "updated": "2026-06-23 18:40:43"
    },
    {
      "ticker": "NDX",
      "label": "纳斯达克100",
      "value": "30,347",
      "pct": "-0.19%",
      "dir": "dn",
      "price": 30347.0801,
      "chg_pct": -0.194,
      "updated": "2026-06-23 18:40:43"
    },
    {
      "ticker": "BTC",
      "label": "比特币/USD",
      "value": "$62,228",
      "pct": "-2.69%",
      "dir": "dn",
      "price": 62228.1289,
      "chg_pct": -2.693,
      "updated": "2026-06-23 18:40:43"
    }
  ]
}