{
  "generated_at": "2026-07-09T16:17:18+08:00",
  "macro": [
    {
      "ticker": "DXY",
      "label": "美元指数",
      "value": "100.89",
      "pct": "-0.08%",
      "dir": "dn",
      "price": 100.895,
      "chg_pct": -0.079,
      "updated": "2026-07-09 16:17:16"
    },
    {
      "ticker": "USDCNY",
      "label": "美元/人民币",
      "value": "6.7932",
      "pct": "-0.13%",
      "dir": "dn",
      "price": 6.7932,
      "chg_pct": -0.129,
      "updated": "2026-07-09 16:17:16"
    },
    {
      "ticker": "US10Y",
      "label": "美债10Y收益率",
      "value": "4.57%",
      "pct": "+0.88%",
      "dir": "up",
      "price": 4.569,
      "chg_pct": 0.883,
      "updated": "2026-07-09 16:17:16"
    },
    {
      "ticker": "VIX",
      "label": "恐慌指数",
      "value": "16.64",
      "pct": "-1.42%",
      "dir": "dn",
      "price": 16.64,
      "chg_pct": -1.422,
      "updated": "2026-07-09 16:17:16"
    },
    {
      "ticker": "NDX",
      "label": "纳斯达克100",
      "value": "29,252",
      "pct": "+0.27%",
      "dir": "up",
      "price": 29252.5605,
      "chg_pct": 0.273,
      "updated": "2026-07-09 16:17:16"
    },
    {
      "ticker": "BTC",
      "label": "比特币/USD",
      "value": "$62,917",
      "pct": "+1.09%",
      "dir": "up",
      "price": 62917.25,
      "chg_pct": 1.092,
      "updated": "2026-07-09 16:17:16"
    }
  ]
}